blackvue_wifi.py
blackvue_wifi-2018.8.12.dist-info/METADATA
blackvue_wifi-2018.8.12.dist-info/RECORD
blackvue_wifi-2018.8.12.dist-info/WHEEL
blackvue_wifi-2018.8.12.dist-info/entry_points.txt
blackvue_wifi-2018.8.12.dist-info/top_level.txt
