Metadata-Version: 2.1
Name: blackvue-wifi
Version: 2018.8.12
Summary: Connect to the HTTP API of BlackVue dashcams over WiFi
Home-page: https://github.com/bartbroere/blackvue-wifi/
Author: Bart Broere
Author-email: maiil@bartbroere.eu
License: MIT License
Keywords: blackvue api dashcam requests http
Platform: UNKNOWN
Classifier: License :: OSI Approved :: MIT License
Classifier: Programming Language :: Python :: 3 :: Only
Classifier: Programming Language :: Python :: 3.4
Classifier: Programming Language :: Python :: 3.5
Classifier: Programming Language :: Python :: 3.6
Classifier: Programming Language :: Python :: 3.7
Classifier: Topic :: Utilities
Requires-Dist: confidence
Requires-Dist: docopt
Requires-Dist: requests
Requires-Dist: tqdm
Requires-Dist: wget
